Workbook

Sheet 01_Assumptions
A1: Legion Health Sponsorship Case — Model Assumptions Ledger
A2: Editable inputs (blue text, yellow fill = Low/Base/High). Live formulas throughout this workbook reference the BASE column (D) of this sheet. Every row carries a status label — never presented as confirmed Legion data unless status begins 'legion_'.
A4: ID | B4: Assumption | C4: Low | D4: Base | E4: High | F4: Unit | G4: Source | H4: Confidence | I4: Decision Impact | J4: Validation Method | K4: Status
A5: A01 | B5: Traditional clinician visit cost (COGS) | C5: 70 | D5: 74 | E5: 85 | F5: USD/visit | G5: CEO-provided directional data (Phase 5, 2026-07-08, data/ceo_data_integration.md #5): ~$74 blended provider COGS per synchronous visit, ~52-53% visit gross margin on ~$153/visit revenue -- internal cross-check passes: (153-74)/153=51.6%, matches CEO's stated 52-53%. REPLACES the prior external telehealth-benchmark placeholder (was $90/150/250, Talkiatry/CareClinic/TherapyRoute anchor). Base=$74 is the CEO point estimate; low=$70/high=$85 are a modest variance band around that single blended figure (not independently sourced -- CEO gave one number, not a range). | H5: medium | I5: high | J5: CEO data | K5: ceo_directional
A6: A02 | B6: AI-supported clinician visit cost (COGS) | C6: 32 | D6: 37 | E6: 45 | F6: USD/visit | G6: CEO-provided directional data (Phase 5, 2026-07-08, data/ceo_data_integration.md #6): AI-leverage assumption ~2x visits/hour -> ~$37 COGS/visit, ~76% gross margin on $153/visit revenue -- internal cross-check passes: (153-37)/153=75.8%, matches CEO's stated '75%+' target. REPLACES the prior unsourced clinician-time-compression placeholder (was $50/90/140). Base=$37 is the CEO point estimate; low=$32/high=$45 are a modest variance band around that single figure (not independently sourced). | H6: medium | I6: high | J6: CEO data | K6: ceo_directional
A7: A02b | B7: Mostly-AI-driven care episode cost | C7: 2 | D7: 8 | E7: 25 | F7: USD/episode | G7: DERIVED, Phase 5 (2026-07-08, data/ceo_data_integration.md #7): fully-loaded episode cost = $1 token/compute cost (CEO data point, compute only) + escalation-allocated human-review cost. Derivation shown explicitly since no Legion escalation-rate figure exists: model an escalated episode as bumping to a full AI-supported-clinician-visit-equivalent review at the A02 base rate (the '$37-leverage cost'), scaled by an illustrative escalation rate (analyst parameter, NOT CEO-sourced) -- low: ~2.7% x $37=$1.00 (+$1 token=$2.00); base: ~18.9% x $37=$7.00 (+$1=$8.00); high: ~64.9% x $37=$24.00 (+$1=$25.00). This lands inside the CEO's own framing ('even generously loaded, episode cost lands ~$2-25') and REPLACES the prior $15/35/75 external-benchmark placeholder. The $1 token input is CEO-directional; the escalation-rate parameter is analyst-derived/illustrative pending a real Legion escalation-rate figure. | H7: medium | I7: high | J7: CEO data + derivation | K7: ceo_directional_derived
A8: A03 | B8: Traditional pathway visits per patient per year | C8: 4 | D8: 5.3 | E8: 13.2 | F8: visits/patient/yr | G8: CEO-provided directional data (Phase 5, 2026-07-08, data/ceo_data_integration.md #2/#3), REPLACES the external-benchmark placeholder (was 4/8/16). Base=5.3 = CEO's stated historical AVERAGE completed visits per patient (implies a ~5-month typical episode per CEO framing). High=13.2 = CEO's stated continuously-active/mature-cohort run-rate (1.08-1.13 completed visits/active-patient/month x 12 = ~13.0-13.6/yr; midpoint used). Low=4 is retained from the prior placeholder's low end as a labeled conservative floor (the CEO did not provide a below-average figure). TENSION, DO NOT SILENTLY BLEND (see model_readme.md v3): base (5.3) is a historical AVERAGE-patient annual rate across a full patient lifecycle; high (13.2) is the rate for a DIFFERENT population -- a patient continuously active all year (mature/retained cohort) -- not simply a more-intensive version of the same average patient. A29/A30 (mature-cohort booked/GM LTV-to-CAC) imply mature-cohort lifetime visits of ~13.2 (2,025/153), ~2.5x the 5.3 historical average; base and high are kept separate per lead direction rather than blended into one number. | H8: medium | I8: high | J8: CEO data | K8: ceo_directional
A9: A03b | B9: AI-supported pathway visits per patient per year | C9: 6 | D9: 12 | E9: 24 | F9: visits/patient/yr | G9: PLACEHOLDER pending Legion data. Assumes AI-supported model enables higher-frequency, shorter touchpoints than traditional cadence; no Legion or external source specific to this pathway definition. | H9: unresolved | I9: medium | J9: CEO data | K9: placeholder_unresolved
A10: A04 | B10: Mostly-AI-driven care episodes per patient per year | C10: 3 | D10: 6 | E10: 12 | F10: episodes/patient/yr | G10: PLACEHOLDER pending Legion data. A 'care episode' here is a bundled unit of AI-driven care (e.g., an AI-led assessment/check-in cycle), analogous in scope to a clinician visit but lower-cost/lower-touch, NOT a single chat message. Range set below A03 (traditional visit cadence) per decision_framework.md's explicit qualitative ordering that the mostly-AI-driven pathway carries the LOWEST relative cost of the three pathways; no direct external benchmark exists for episode frequency specifically, so the range is an analytic placeholder anchored to that qualitative constraint. | H10: unresolved | I10: medium | J10: CEO data | K10: placeholder_unresolved
A11: A05 | B11: Sponsor ARPU (fixed-fee sponsorship per exposed patient) | C11: 10 | D11: 15 | E11: 40 | F11: USD/patient/yr | G11: comparable_notes.md: GoodRx pharma-solutions ARPU ~$15/user/yr (derived); high case assumes multi-sponsor stacking (estimate) | H11: low | I11: high | J11: Sponsor-side test (15-20 buyer interviews) | K11: estimated_external
A12: A06 | B12: Programmatic health eCPM (patient-vertical contextual) | C12: 20 | D12: 30 | E12: 45 | F12: USD/1000 impressions | G12: comparable_notes.md: Facebook healthcare / patient-health-vertical CPM benchmarks; do NOT use physician CPMs ($70-1000+) | H12: medium | I12: medium | J12: Research benchmarks | K12: estimated_external
A13: A06b | B13: Ad sessions per patient per year (Model A exposure volume) | C13: 12 | D13: 52 | E13: 450 | F13: sessions/patient/yr | G13: PLACEHOLDER. Low/base derived from A03/A03b/A04 order-of-magnitude (roughly monthly to several-times-weekly touchpoints); no Legion product-usage data exists yet. HIGH END WIDENED post strategy_red_team.md Attack 1.3 (2026-07-07 v2 revision): 150/yr was anchored to visit-based cadences and did not represent how a daily-use ambient-engagement AI companion/chat product might actually be opened; 450/yr (~1.2x/day) represents that daily-use ceiling instead. Still no Legion product-usage data exists for either end. | H13: unresolved | I13: medium | J13: Product analytics (post-launch) | K13: placeholder_unresolved
A14: A06c | B14: Ads served per session | C14: 1 | D14: 2 | E14: 3 | F14: ads/session | G14: PLACEHOLDER external analogy to typical content-page ad density (display/native); not Legion-specific and no clinical-workflow ad placement has been designed or approved. | H14: low | I14: medium | J14: Product design decision | K14: placeholder_external
A15: A06d | B15: Ad fill rate | C15: 50 | D15: 70 | E15: 90 | F15: % (0-100) | G15: PLACEHOLDER general programmatic display fill-rate norms (50-90% typical range cited across ad-tech industry sources); not health-vertical specific. Stored as 0-100 (not 0-1) for consistency with other pct01-converted assumptions (A07/A14/A19/A21/A22) in scenarios.py/sensitivity.py. | H15: low | I15: low | J15: Ad-ops benchmarking | K15: placeholder_external
A16: A06e | B16: Platform/ad-tech fee (take rate) | C16: 20 | D16: 30 | E16: 40 | F16: % (0-100) | G16: PLACEHOLDER standard programmatic ad-exchange take rates (20-40% commonly cited industry-wide for SSP/DSP/exchange fees combined). Stored as 0-100 (not 0-1) for consistency with other pct01-converted assumptions. | H16: low | I16: medium | J16: Ad-ops benchmarking | K16: placeholder_external
... A40: A30 | B40: Mature-cohort gross-margin LTV/CAC multiple | C40: 4.2 | D40: 4.2 | E40: 4.2 | F40: x (LTV/CAC ratio) | G40: CEO-provided directional data (Phase 5, 2026-07-08, data/ceo_data_integration.md #9): mature-cohort gross-margin LTV/CAC ~4.2x. Single point estimate (no range given). Implies gross-margin LTV ~= 4.2 x $250 (A28) = $1,050/patient. Context/cross-check only -- not wired into any pathway/model formula in model.py. | H40: medium | I40: low | J40: CEO data | K40: ceo_directional
A42: Status legend:
A43: - placeholder_unresolved / awaiting_data / awaiting_research = no external or Legion source yet; analytic placeholder only.
A44: - placeholder_external = PLACEHOLDER pending Legion data, anchored to an external benchmark (see Source column).
A45: - estimated_external = sourced to an external comparable (research/comparable_notes.md); not Legion data.
A46: - set_provisional = lead-judgment policy lever (e.g., target margin), not an empirical estimate.
A47: - ceo_directional (NEW, Phase 5, 2026-07-08) = founder-provided directional estimate (data/ceo_data_integration.md); confidence medium -- better than an external benchmark, but not an audited Legion export.
A48: - ceo_directional_derived (NEW, Phase 5) = built from a CEO-provided directional figure plus an explicit, shown analyst derivation (see A02b notes); the CEO input itself is directional, the derivation math is analyst judgment.
A49: - NONE of these rows are Legion-confirmed audited data, including the ceo_directional rows above. Replace with Legion actuals as they arrive (see model_readme.md).

Sheet 02_Unit_Economics
A1: Unit Economics — Three Care Pathways
A2: Care-delivery (COGS-only) cost and fully loaded incremental cost per patient per year, by pathway. All cells reference 01_Assumptions live (Base column unless noted). See model.py for formula source.
A4: 1. Care-Delivery Cost per Patient per Year (COGS only) — Low / Base / High
A5: Pathway | B5: Cost/unit assumption | C5: Units/patient/yr assumption | D5: Cost — Low | E5: Cost — Base | F5: Cost — High | G5: Formula
A6: Traditional clinician visit | B6: A01 (cost/unit) | C6: A03 (units/yr) | D6: ='01_Assumptions'!C5*'01_Assumptions'!C8 | E6: ='01_Assumptions'!D5*'01_Assumptions'!D8 | F6: ='01_Assumptions'!E5*'01_Assumptions'!E8 | G6: cost_per_unit x units_per_patient_per_yr
A7: AI-supported clinician care | B7: A02 (cost/unit) | C7: A03b (units/yr) | D7: ='01_Assumptions'!C6*'01_Assumptions'!C9 | E7: ='01_Assumptions'!D6*'01_Assumptions'!D9 | F7: ='01_Assumptions'!E6*'01_Assumptions'!E9 | G7: cost_per_unit x units_per_patient_per_yr
A8: Mostly-AI-driven care episode | B8: A02b (cost/unit) | C8: A04 (units/yr) | D8: ='01_Assumptions'!C7*'01_Assumptions'!C10 | E8: ='01_Assumptions'!D7*'01_Assumptions'!D10 | F8: ='01_Assumptions'!E7*'01_Assumptions'!E10 | G8: cost_per_unit x units_per_patient_per_yr
A10: 2. Fully Loaded Incremental Cost per Patient per Year (Base Case) — by Pathway
A11: Note: sponsor-servicing, commercial, and compliance costs are allocated per patient and do not vary by pathway (they depend on sponsor-contract structure and eligible population, A08/A09/A23/A13). Trust-churn cost uses the Model B external-anchor ARPU (A05 Base) as the revenue-at-risk proxy, matching sensitivity.py's break-even solver convention (documented there as a stable approximation since trust cost is a small share of ARPU). Core-Book Contagion (NEW v2, added post strategy_red_team.md Attack #5/2.5) is a SECOND, separate trust-cost term netting a placeholder spillover rate (A26) against Legion's EXISTING core fee-for-service revenue per patient (A25), not sponsor-tier ARPU — included in every row, base value deliberately small so it remains visibly provisional.
A12: Pathway | B12: Care Delivery | C12: Sponsor Servicing | D12: Commercial (Sales) | E12: Compliance/Legal | F12: Trust/Churn (Sponsor-Tier) | G12: Core-Book Contagion (NEW v2) | H12: Fully Loaded Cost | I12: Required ARPU @ m=25%
A13: Traditional clinician visit | B13: =E6 | C13: =0.5*('01_Assumptions'!D18*'01_Assumptions'!D33)/'01_Assumptions'!D23 | D13: =0.5*('01_Assumptions'!D18*'01_Assumptions'!D33)/'01_Assumptions'!D23 | E13: ='01_Assumptions'!D19/'01_Assumptions'!D23 | F13: ='01_Assumptions'!D11*('01_Assumptions'!D20+'01_Assumptions'!D21)/100 | G13: ='01_Assumptions'!D35*'01_Assumptions'!D36/100 | H13: =B13+C13+D13+E13+F13+G13 | I13: =H13/(1-'01_Assumptions'!D24/100)
A14: AI-supported clinician care | B14: =E7 | C14: =0.5*('01_Assumptions'!D18*'01_Assumptions'!D33)/'01_Assumptions'!D23 | D14: =0.5*('01_Assumptions'!D18*'01_Assumptions'!D33)/'01_Assumptions'!D23 | E14: ='01_Assumptions'!D19/'01_Assumptions'!D23 | F14: ='01_Assumptions'!D11*('01_Assumptions'!D20+'01_Assumptions'!D21)/100 | G14: ='01_Assumptions'!D35*'01_Assumptions'!D36/100 | H14: =B14+C14+D14+E14+F14+G14 | I14: =H14/(1-'01_Assumptions'!D24/100)
A15: Mostly-AI-driven care episode | B15: =E8 | C15: =0.5*('01_Assumptions'!D18*'01_Assumptions'!D33)/'01_Assumptions'!D23 | D15: =0.5*('01_Assumptions'!D18*'01_Assumptions'!D33)/'01_Assumptions'!D23 | E15: ='01_Assumptions'!D19/'01_Assumptions'!D23 | F15: ='01_Assumptions'!D11*('01_Assumptions'!D20+'01_Assumptions'!D21)/100 | G15: ='01_Assumptions'!D35*'01_Assumptions'!D36/100 | H15: =B15+C15+D15+E15+F15+G15 | I15: =H15/(1-'01_Assumptions'!D24/100)
A17: 3. Gross Margin vs. Contribution Margin (illustrative, using Model B external-anchor ARPU)
A18: Gross margin nets out care-delivery COGS only. Contribution margin nets out the FULL loaded cost (care + servicing + commercial + compliance + trust + core-book contagion, NEW v2). Legion's reported ~53% visit gross margin (CEO context, not modeled here) is the narrower measure.
A19: Pathway | B19: Illustrative Revenue (Model B anchor ARPU) | C19: Care-Delivery Cost | D19: Gross Margin % | E19: Fully Loaded Cost | F19: Contribution Margin %
A20: Traditional clinician visit | B20: ='01_Assumptions'!D11*'01_Assumptions'!D17/100 | C20: =E6 | D20: =(B20-C20)/B20 | E20: =H13 | F20: =(B20-E20)/B20
A21: AI-supported clinician care | B21: ='01_Assumptions'!D11*'01_Assumptions'!D17/100 | C21: =E7 | D21: =(B21-C21)/B21 | E21: =H14 | F21: =(B21-E21)/B21
A22: Mostly-AI-driven care episode | B22: ='01_Assumptions'!D11*'01_Assumptions'!D17/100 | C22: =E8 | D22: =(B22-C22)/B22 | E22: =H15 | F22: =(B22-E22)/B22

Sheet 03_Monetization_Models
A1: Monetization Models A-E — Base-Case ARPU and Pathway x Model Grid
A2: All formulas reference 01_Assumptions (Base column) live.
A4: Model A — Programmatic Advertising
A5: impressions/patient/yr = sessions x ads/session x fill%
A6: Impressions/patient/yr | B6: ='01_Assumptions'!D13*'01_Assumptions'!D14*'01_Assumptions'!D15/100
A7: Gross ad revenue/patient/yr (impressions x eCPM/1000) | B7: =B6*'01_Assumptions'!D12/1000
A8: Net ARPU (Model A) after platform fee | B8: =B7*(1-'01_Assumptions'!D16/100)
A10: Model B — Fixed-Fee Sponsorship
A11: Gross ARPU = (sponsors x contract value) / exposed patients [A23 x A24 / A13] | B11: =('01_Assumptions'!D33*'01_Assumptions'!D34)/'01_Assumptions'!D23
A12: Less: sales+servicing cost per patient [A08 x A23 / A13] | B12: =('01_Assumptions'!D18*'01_Assumptions'!D33)/'01_Assumptions'!D23
A13: Net ARPU (formula-derived, cost-allocation cross-check) | B13: =B11-B12
A14: External-anchor ARPU (A05) x sponsor renewal rate (A07) — USED IN GRID BELOW | B14: ='01_Assumptions'!D11*'01_Assumptions'!D17/100
A16: Model C — Performance Partnership [FLAG: legal review required, model only — steering risk]
A17: Qualified actions/patient/yr = (action rate % ) x 12 months | B17: ='01_Assumptions'!D29/100*12
A18: ARPU (Model C) = actions/yr x revenue/action | B18: =B17*'01_Assumptions'!D30
A20: Model D — Employer/Payer Underwriting
A21: PMPM = A15 (USD/patient/yr) / 12 | B21: ='01_Assumptions'!D25/12
A22: ARPU (Model D) = PMPM x 12 x utilization adjustment % | B22: =B21*12*'01_Assumptions'!D31/100
A24: Model E — Foundation/Nonprofit Underwriting
A25: ARPU (Model E) = grant $/yr / cohort size | B25: ='01_Assumptions'!D26/'01_Assumptions'!D27
A27: Base-Case Grid: Pathway x Model — Required vs. Actual ARPU, Gap, North-Star Margin
A28: Reproduces the base-case rows of outputs.csv (scenarios.py) with live formulas. North-star = risk-adjusted contribution margin per eligible patient per year (sponsor revenue - care cost - servicing - commercial - compliance - trust churn - core-book contagion, NEW v2). FIXED (Phase 5, 2026-07-08): this grid previously omitted the core-book contagion term from Fully Loaded Cost/North-Star entirely (understating both by A25xA26/100, ~$4.06/patient/yr at the new base case) -- added as its own column below so this tab now matches outputs.csv exactly.
A29: Pathway | B29: Model | C29: Care Delivery Cost | D29: Sponsor Servicing | E29: Commercial | F29: Compliance | G29: Trust/Churn Cost | H29: Core-Book Contagion (NEW v2) | I29: Fully Loaded Cost | J29: Required ARPU (m=25%) | K29: Actual ARPU | L29: North-Star ($/patient/yr)
A30: Traditional clinician visit | B30: A. Programmatic Ads | C30: ='02_Unit_Economics'!E6 | D30: ='02_Unit_Economics'!C13 | E30: ='02_Unit_Economics'!D13 | F30: ='02_Unit_Economics'!E13 | G30: =B8*('01_Assumptions'!D20+'01_Assumptions'!D21)/100 | H30: ='02_Unit_Economics'!G13 | I30: =C30+D30+E30+F30+G30+H30 | J30: =I30/(1-'01_Assumptions'!D24/100) | K30: =B8 | L30: =K30-C30-D30-E30-F30-G30-H30
A31: Traditional clinician visit | B31: B. Fixed-Fee Sponsorship | C31: ='02_Unit_Economics'!E6 | D31: ='02_Unit_Economics'!C13 | E31: ='02_Unit_Economics'!D13 | F31: ='02_Unit_Economics'!E13 | G31: =B14*('01_Assumptions'!D20+'01_Assumptions'!D21)/100 | H31: ='02_Unit_Economics'!G13 | I31: =C31+D31+E31+F31+G31+H31 | J31: =I31/(1-'01_Assumptions'!D24/100) | K31: =B14 | L31: =K31-C31-D31-E31-F31-G31-H31
A32: Traditional clinician visit | B32: C. Performance Partnership (legal review req'd) | C32: ='02_Unit_Economics'!E6 | D32: ='02_Unit_Economics'!C13 | E32: ='02_Unit_Economics'!D13 | F32: ='02_Unit_Economics'!E13 | G32: =B18*('01_Assumptions'!D20+'01_Assumptions'!D21)/100 | H32: ='02_Unit_Economics'!G13 | I32: =C32+D32+E32+F32+G32+H32 | J32: =I32/(1-'01_Assumptions'!D24/100) | K32: =B18 | L32: =K32-C32-D32-E32-F32-G32-H32
A33: Traditional clinician visit | B33: D. Employer/Payer Underwriting | C33: ='02_Unit_Economics'!E6 | D33: ='02_Unit_Economics'!C13 | E33: ='02_Unit_Economics'!D13 | F33: ='02_Unit_Economics'!E13 | G33: =B22*('01_Assumptions'!D20+'01_Assumptions'!D21)/100 | H33: ='02_Unit_Economics'!G13 | I33: =C33+D33+E33+F33+G33+H33 | J33: =I33/(1-'01_Assumptions'!D24/100) | K33: =B22 | L33: =K33-C33-D33-E33-F33-G33-H33
A34: Traditional clinician visit | B34: E. Foundation Underwriting | C34: ='02_Unit_Economics'!E6 | D34: ='02_Unit_Economics'!C13 | E34: ='02_Unit_Economics'!D13 | F34: ='02_Unit_Economics'!E13 | G34: =B25*('01_Assumptions'!D20+'01_Assumptions'!D21)/100 | H34: ='02_Unit_Economics'!G13 | I34: =C34+D34+E34+F34+G34+H34 | J34: =I34/(1-'01_Assumptions'!D24/100) | K34: =B25 | L34: =K34-C34-D34-E34-F34-G34-H34
A35: AI-supported clinician care | B35: A. Programmatic Ads | C35: ='02_Unit_Economics'!E7 | D35: ='02_Unit_Economics'!C14 | E35: ='02_Unit_Economics'!D14 | F35: ='02_Unit_Economics'!E14 | G35: =B8*('01_Assumptions'!D20+'01_Assumptions'!D21)/100 | H35: ='02_Unit_Economics'!G14 | I35: =C35+D35+E35+F35+G35+H35 | J35: =I35/(1-'01_Assumptions'!D24/100) | K35: =B8 | L35: =K35-C35-D35-E35-F35-G35-H35
A36: AI-supported clinician care | B36: B. Fixed-Fee Sponsorship | C36: ='02_Unit_Economics'!E7 | D36: ='02_Unit_Economics'!C14 | E36: ='02_Unit_Economics'!D14 | F36: ='02_Unit_Economics'!E14 | G36: =B14*('01_Assumptions'!D20+'01_Assumptions'!D21)/100 | H36: ='02_Unit_Economics'!G14 | I36: =C36+D36+E36+F36+G36+H36 | J36: =I36/(1-'01_Assumptions'!D24/100) | K36: =B14 | L36: =K36-C36-D36-E36-F36-G36-H36
A37: AI-supported clinician care | B37: C. Performance Partnership (legal review req'd) | C37: ='02_Unit_Economics'!E7 | D37: ='02_Unit_Economics'!C14 | E37: ='02_Unit_Economics'!D14 | F37: ='02_Unit_Economics'!E14 | G37: =B18*('01_Assumptions'!D20+'01_Assumptions'!D21)/100 | H37: ='02_Unit_Economics'!G14 | I37: =C37+D37+E37+F37+G37+H37 | J37: =I37/(1-'01_Assumptions'!D24/100) | K37: =B18 | L37: =K37-C37-D37-E37-F37-G37-H37
A38: AI-supported clinician care | B38: D. Employer/Payer Underwriting | C38: ='02_Unit_Economics'!E7 | D38: ='02_Unit_Economics'!C14 | E38: ='02_Unit_Economics'!D14 | F38: ='02_Unit_Economics'!E14 | G38: =B22*('01_Assumptions'!D20+'01_Assumptions'!D21)/100 | H38: ='02_Unit_Economics'!G14 | I38: =C38+D38+E38+F38+G38+H38 | J38: =I38/(1-'01_Assumptions'!D24/100) | K38: =B22 | L38: =K38-C38-D38-E38-F38-G38-H38
A39: AI-supported clinician care | B39: E. Foundation Underwriting | C39: ='02_Unit_Economics'!E7 | D39: ='02_Unit_Economics'!C14 | E39: ='02_Unit_Economics'!D14 | F39: ='02_Unit_Economics'!E14 | G39: =B25*('01_Assumptions'!D20+'01_Assumptions'!D21)/100 | H39: ='02_Unit_Economics'!G14 | I39: =C39+D39+E39+F39+G39+H39 | J39: =I39/(1-'01_Assumptions'!D24/100) | K39: =B25 | L39: =K39-C39-D39-E39-F39-G39-H39
A40: Mostly-AI-driven care episode | B40: A. Programmatic Ads | C40: ='02_Unit_Economics'!E8 | D40: ='02_Unit_Economics'!C15 | E40: ='02_Unit_Economics'!D15 | F40: ='02_Unit_Economics'!E15 | G40: =B8*('01_Assumptions'!D20+'01_Assumptions'!D21)/100 | H40: ='02_Unit_Economics'!G15 | I40: =C40+D40+E40+F40+G40+H40 | J40: =I40/(1-'01_Assumptions'!D24/100) | K40: =B8 | L40: =K40-C40-D40-E40-F40-G40-H40
A41: Mostly-AI-driven care episode | B41: B. Fixed-Fee Sponsorship | C41: ='02_Unit_Economics'!E8 | D41: ='02_Unit_Economics'!C15 | E41: ='02_Unit_Economics'!D15 | F41: ='02_Unit_Economics'!E15 | G41: =B14*('01_Assumptions'!D20+'01_Assumptions'!D21)/100 | H41: ='02_Unit_Economics'!G15 | I41: =C41+D41+E41+F41+G41+H41 | J41: =I41/(1-'01_Assumptions'!D24/100) | K41: =B14 | L41: =K41-C41-D41-E41-F41-G41-H41
A42: Mostly-AI-driven care episode | B42: C. Performance Partnership (legal review req'd) | C42: ='02_Unit_Economics'!E8 | D42: ='02_Unit_Economics'!C15 | E42: ='02_Unit_Economics'!D15 | F42: ='02_Unit_Economics'!E15 | G42: =B18*('01_Assumptions'!D20+'01_Assumptions'!D21)/100 | H42: ='02_Unit_Economics'!G15 | I42: =C42+D42+E42+F42+G42+H42 | J42: =I42/(1-'01_Assumptions'!D24/100) | K42: =B18 | L42: =K42-C42-D42-E42-F42-G42-H42
A43: Mostly-AI-driven care episode | B43: D. Employer/Payer Underwriting | C43: ='02_Unit_Economics'!E8 | D43: ='02_Unit_Economics'!C15 | E43: ='02_Unit_Economics'!D15 | F43: ='02_Unit_Economics'!E15 | G43: =B22*('01_Assumptions'!D20+'01_Assumptions'!D21)/100 | H43: ='02_Unit_Economics'!G15 | I43: =C43+D43+E43+F43+G43+H43 | J43: =I43/(1-'01_Assumptions'!D24/100) | K43: =B22 | L43: =K43-C43-D43-E43-F43-G43-H43
A44: Mostly-AI-driven care episode | B44: E. Foundation Underwriting | C44: ='02_Unit_Economics'!E8 | D44: ='02_Unit_Economics'!C15 | E44: ='02_Unit_Economics'!D15 | F44: ='02_Unit_Economics'!E15 | G44: =B25*('01_Assumptions'!D20+'01_Assumptions'!D21)/100 | H44: ='02_Unit_Economics'!G15 | I44: =C44+D44+E44+F44+G44+H44 | J44: =I44/(1-'01_Assumptions'!D24/100) | K44: =B25 | L44: =K44-C44-D44-E44-F44-G44-H44

Sheet 04_Path_to_1B
A1: Valuation Backsolve — Path to a ~$1B Valuation
A2: required_revenue = target_valuation / revenue_multiple; required_patients = required_revenue / ARPU
A4: Target valuation (USD) | B4: 1000000000
A6: Required Revenue at Each Revenue Multiple
A7: Multiple (x revenue) | B7: Required Annual Revenue
A8: 5x | B8: =$B$4/5
A9: 10x | B9: =$B$4/10
A10: 15x | B10: =$B$4/15
A11: 20x | B11: =$B$4/20
A13: Required Active Patients by Model (Base-Case ARPU) and Multiple
A14: Model | B14: Base ARPU (USD/patient/yr) | C14: Req'd Patients @ 5x | D14: Req'd Patients @ 10x | E14: Req'd Patients @ 15x | F14: Req'd Patients @ 20x
A15: A. Programmatic Ads | B15: ='03_Monetization_Models'!B8 | C15: =IF(B15<=0,"n/a (non-positive ARPU)",B8/B15) | D15: =IF(B15<=0,"n/a (non-positive ARPU)",B9/B15) | E15: =IF(B15<=0,"n/a (non-positive ARPU)",B10/B15) | F15: =IF(B15<=0,"n/a (non-positive ARPU)",B11/B15)
A16: B. Fixed-Fee Sponsorship | B16: ='03_Monetization_Models'!B14 | C16: =IF(B16<=0,"n/a (non-positive ARPU)",B8/B16) | D16: =IF(B16<=0,"n/a (non-positive ARPU)",B9/B16) | E16: =IF(B16<=0,"n/a (non-positive ARPU)",B10/B16) | F16: =IF(B16<=0,"n/a (non-positive ARPU)",B11/B16)
A17: C. Performance Partnership (legal review req'd) | B17: ='03_Monetization_Models'!B18 | C17: =IF(B17<=0,"n/a (non-positive ARPU)",B8/B17) | D17: =IF(B17<=0,"n/a (non-positive ARPU)",B9/B17) | E17: =IF(B17<=0,"n/a (non-positive ARPU)",B10/B17) | F17: =IF(B17<=0,"n/a (non-positive ARPU)",B11/B17)
A18: D. Employer/Payer Underwriting | B18: ='03_Monetization_Models'!B22 | C18: =IF(B18<=0,"n/a (non-positive ARPU)",B8/B18) | D18: =IF(B18<=0,"n/a (non-positive ARPU)",B9/B18) | E18: =IF(B18<=0,"n/a (non-positive ARPU)",B10/B18) | F18: =IF(B18<=0,"n/a (non-positive ARPU)",B11/B18)
A19: E. Foundation Underwriting | B19: ='03_Monetization_Models'!B25 | C19: =IF(B19<=0,"n/a (non-positive ARPU)",B8/B19) | D19: =IF(B19<=0,"n/a (non-positive ARPU)",B9/B19) | E19: =IF(B19<=0,"n/a (non-positive ARPU)",B10/B19) | F19: =IF(B19<=0,"n/a (non-positive ARPU)",B11/B19)
A21: Model B — Required Sponsor Count and Implied Concentration (equal-weight contracts)
A22: Uses A24 (reference annual contract value) as the per-sponsor contract size. concentration_pct_per_sponsor = 1 / required_sponsors (equal-weight assumption).
A23: Multiple | B23: Required Revenue | C23: Reference Contract Value (A24) | D23: Required Sponsors | E23: Concentration % / Sponsor
A24: 5x | B24: =B8 | C24: ='01_Assumptions'!D34 | D24: =B24/C24 | E24: =1/D24
A25: 10x | B25: =B9 | C25: ='01_Assumptions'!D34 | D25: =B25/C25 | E25: =1/D25
A26: 15x | B26: =B10 | C26: ='01_Assumptions'!D34 | D26: =B26/C26 | E26: =1/D26
A27: 20x | B27: =B11 | C27: ='01_Assumptions'!D34 | D27: =B27/C27 | E27: =1/D27

Sheet 05_Sensitivity
A1: Sensitivity — Break-Even Sponsor ARPU and One-Way Tornado
A2: Break-even ARPU table is fully live (all 3 pathways). The tornado table below is illustrative for the single base-case combo with a positive north-star margin (ai_driven pathway x Model D); it flexes one assumption to its Low/High value while holding all others at Base, mirroring sensitivity.py's method. The full 195-row tornado (all 3 pathways x 5 models x 13 assumptions) is in sensitivity_outputs.csv.
A4: Break-Even Sponsor ARPU per Pathway (Base-Case Cost)
A5: Pathway | B5: Fully Loaded Cost | C5: Break-Even ARPU (m=0%) | D5: Break-Even ARPU (m=20%) | E5: Break-Even ARPU (m=25%) | F5: Break-Even ARPU (m=30%) | G5: External Anchor ARPU (A05 Base) | H5: Gap to Anchor @ m=25%
A6: Traditional clinician visit | B6: ='02_Unit_Economics'!H13 | C6: =B6/(1-0) | D6: =B6/(1-0.20) | E6: =B6/(1-0.25) | F6: =B6/(1-0.30) | G6: ='01_Assumptions'!D11 | H6: =G6-E6
A7: AI-supported clinician care | B7: ='02_Unit_Economics'!H14 | C7: =B7/(1-0) | D7: =B7/(1-0.20) | E7: =B7/(1-0.25) | F7: =B7/(1-0.30) | G7: ='01_Assumptions'!D11 | H7: =G7-E7
A8: Mostly-AI-driven care episode | B8: ='02_Unit_Economics'!H15 | C8: =B8/(1-0) | D8: =B8/(1-0.20) | E8: =B8/(1-0.25) | F8: =B8/(1-0.30) | G8: ='01_Assumptions'!D11 | H8: =G8-E8
A10: Illustrative One-Way Tornado — ai_driven Pathway x Model D (Employer/Payer Underwriting)
A11: Base-case north-star margin for this combo: | B11: ='03_Monetization_Models'!L43
A12: Assumption Flexed | B12: North-Star @ Low | C12: North-Star @ High | D12: Swing (abs $)
A13: A15: Sponsor ARPU - employer PEPM rate (Model D anchor) | B13: =(('01_Assumptions'!C25/12)*12*('01_Assumptions'!D31/100))-('01_Assumptions'!D7*'01_Assumptions'!D10)-(0.5*('01_Assumptions'!D18*'01_Assumptions'!D33)/'01_Assumptions'!D23)-(0.5*('01_Assumptions'!D18*'01_Assumptions'!D33)/'01_Assumptions'!D23)-('01_Assumptions'!D19/'01_Assumptions'!D23)-((('01_Assumptions'!C25/12)*12*('01_Assumptions'!D31/100))*('01_Assumptions'!D20+'01_Assumptions'!D21)/100)-('01_Assumptions'!D35*'01_Assumptions'!D36/100) | C13: =(('01_Assumptions'!E25/12)*12*('01_Assumptions'!D31/100))-('01_Assumptions'!D7*'01_Assumptions'!D10)-(0.5*('01_Assumptions'!D18*'01_Assumptions'!D33)/'01_Assumptions'!D23)-(0.5*('01_Assumptions'!D18*'01_Assumptions'!D33)/'01_Assumptions'!D23)-('01_Assumptions'!D19/'01_Assumptions'!D23)-((('01_Assumptions'!E25/12)*12*('01_Assumptions'!D31/100))*('01_Assumptions'!D20+'01_Assumptions'!D21)/100)-('01_Assumptions'!D35*'01_Assumptions'!D36/100) | D13: =ABS(C13-B13)
A14: A02b: Care cost - AI-driven episode | B14: =(('01_Assumptions'!D25/12)*12*('01_Assumptions'!D31/100))-('01_Assumptions'!C7*'01_Assumptions'!D10)-(0.5*('01_Assumptions'!D18*'01_Assumptions'!D33)/'01_Assumptions'!D23)-(0.5*('01_Assumptions'!D18*'01_Assumptions'!D33)/'01_Assumptions'!D23)-('01_Assumptions'!D19/'01_Assumptions'!D23)-((('01_Assumptions'!D25/12)*12*('01_Assumptions'!D31/100))*('01_Assumptions'!D20+'01_Assumptions'!D21)/100)-('01_Assumptions'!D35*'01_Assumptions'!D36/100) | C14: =(('01_Assumptions'!D25/12)*12*('01_Assumptions'!D31/100))-('01_Assumptions'!E7*'01_Assumptions'!D10)-(0.5*('01_Assumptions'!D18*'01_Assumptions'!D33)/'01_Assumptions'!D23)-(0.5*('01_Assumptions'!D18*'01_Assumptions'!D33)/'01_Assumptions'!D23)-('01_Assumptions'!D19/'01_Assumptions'!D23)-((('01_Assumptions'!D25/12)*12*('01_Assumptions'!D31/100))*('01_Assumptions'!D20+'01_Assumptions'!D21)/100)-('01_Assumptions'!D35*'01_Assumptions'!D36/100) | D14: =ABS(C14-B14)
A15: A21: Engagement - employer utilization adjustment | B15: =(('01_Assumptions'!D25/12)*12*('01_Assumptions'!C31/100))-('01_Assumptions'!D7*'01_Assumptions'!D10)-(0.5*('01_Assumptions'!D18*'01_Assumptions'!D33)/'01_Assumptions'!D23)-(0.5*('01_Assumptions'!D18*'01_Assumptions'!D33)/'01_Assumptions'!D23)-('01_Assumptions'!D19/'01_Assumptions'!D23)-((('01_Assumptions'!D25/12)*12*('01_Assumptions'!C31/100))*('01_Assumptions'!D20+'01_Assumptions'!D21)/100)-('01_Assumptions'!D35*'01_Assumptions'!D36/100) | C15: =(('01_Assumptions'!D25/12)*12*('01_Assumptions'!E31/100))-('01_Assumptions'!D7*'01_Assumptions'!D10)-(0.5*('01_Assumptions'!D18*'01_Assumptions'!D33)/'01_Assumptions'!D23)-(0.5*('01_Assumptions'!D18*'01_Assumptions'!D33)/'01_Assumptions'!D23)-('01_Assumptions'!D19/'01_Assumptions'!D23)-((('01_Assumptions'!D25/12)*12*('01_Assumptions'!E31/100))*('01_Assumptions'!D20+'01_Assumptions'!D21)/100)-('01_Assumptions'!D35*'01_Assumptions'!D36/100) | D15: =ABS(C15-B15)
A16: A11: Trust churn - retention loss | B16: =(('01_Assumptions'!D25/12)*12*('01_Assumptions'!D31/100))-('01_Assumptions'!D7*'01_Assumptions'!D10)-(0.5*('01_Assumptions'!D18*'01_Assumptions'!D33)/'01_Assumptions'!D23)-(0.5*('01_Assumptions'!D18*'01_Assumptions'!D33)/'01_Assumptions'!D23)-('01_Assumptions'!D19/'01_Assumptions'!D23)-((('01_Assumptions'!D25/12)*12*('01_Assumptions'!D31/100))*('01_Assumptions'!D20+'01_Assumptions'!C21)/100)-('01_Assumptions'!D35*'01_Assumptions'!D36/100) | C16: =(('01_Assumptions'!D25/12)*12*('01_Assumptions'!D31/100))-('01_Assumptions'!D7*'01_Assumptions'!D10)-(0.5*('01_Assumptions'!D18*'01_Assumptions'!D33)/'01_Assumptions'!D23)-(0.5*('01_Assumptions'!D18*'01_Assumptions'!D33)/'01_Assumptions'!D23)-('01_Assumptions'!D19/'01_Assumptions'!D23)-((('01_Assumptions'!D25/12)*12*('01_Assumptions'!D31/100))*('01_Assumptions'!D20+'01_Assumptions'!E21)/100)-('01_Assumptions'!D35*'01_Assumptions'!D36/100) | D16: =ABS(C16-B16)
A17: A13: Eligible patient volume | B17: =(('01_Assumptions'!D25/12)*12*('01_Assumptions'!D31/100))-('01_Assumptions'!D7*'01_Assumptions'!D10)-(0.5*('01_Assumptions'!D18*'01_Assumptions'!D33)/'01_Assumptions'!C23)-(0.5*('01_Assumptions'!D18*'01_Assumptions'!D33)/'01_Assumptions'!C23)-('01_Assumptions'!D19/'01_Assumptions'!C23)-((('01_Assumptions'!D25/12)*12*('01_Assumptions'!D31/100))*('01_Assumptions'!D20+'01_Assumptions'!D21)/100)-('01_Assumptions'!D35*'01_Assumptions'!D36/100) | C17: =(('01_Assumptions'!D25/12)*12*('01_Assumptions'!D31/100))-('01_Assumptions'!D7*'01_Assumptions'!D10)-(0.5*('01_Assumptions'!D18*'01_Assumptions'!D33)/'01_Assumptions'!E23)-(0.5*('01_Assumptions'!D18*'01_Assumptions'!D33)/'01_Assumptions'!E23)-('01_Assumptions'!D19/'01_Assumptions'!E23)-((('01_Assumptions'!D25/12)*12*('01_Assumptions'!D31/100))*('01_Assumptions'!D20+'01_Assumptions'!D21)/100)-('01_Assumptions'!D35*'01_Assumptions'!D36/100) | D17: =ABS(C17-B17)
A18: A10: Trust churn - booking conversion loss | B18: =(('01_Assumptions'!D25/12)*12*('01_Assumptions'!D31/100))-('01_Assumptions'!D7*'01_Assumptions'!D10)-(0.5*('01_Assumptions'!D18*'01_Assumptions'!D33)/'01_Assumptions'!D23)-(0.5*('01_Assumptions'!D18*'01_Assumptions'!D33)/'01_Assumptions'!D23)-('01_Assumptions'!D19/'01_Assumptions'!D23)-((('01_Assumptions'!D25/12)*12*('01_Assumptions'!D31/100))*('01_Assumptions'!C20+'01_Assumptions'!D21)/100)-('01_Assumptions'!D35*'01_Assumptions'!D36/100) | C18: =(('01_Assumptions'!D25/12)*12*('01_Assumptions'!D31/100))-('01_Assumptions'!D7*'01_Assumptions'!D10)-(0.5*('01_Assumptions'!D18*'01_Assumptions'!D33)/'01_Assumptions'!D23)-(0.5*('01_Assumptions'!D18*'01_Assumptions'!D33)/'01_Assumptions'!D23)-('01_Assumptions'!D19/'01_Assumptions'!D23)-((('01_Assumptions'!D25/12)*12*('01_Assumptions'!D31/100))*('01_Assumptions'!E20+'01_Assumptions'!D21)/100)-('01_Assumptions'!D35*'01_Assumptions'!D36/100) | D18: =ABS(C18-B18)
A19: A08: Sales/servicing cost per contract | B19: =(('01_Assumptions'!D25/12)*12*('01_Assumptions'!D31/100))-('01_Assumptions'!D7*'01_Assumptions'!D10)-(0.5*('01_Assumptions'!C18*'01_Assumptions'!D33)/'01_Assumptions'!D23)-(0.5*('01_Assumptions'!C18*'01_Assumptions'!D33)/'01_Assumptions'!D23)-('01_Assumptions'!D19/'01_Assumptions'!D23)-((('01_Assumptions'!D25/12)*12*('01_Assumptions'!D31/100))*('01_Assumptions'!D20+'01_Assumptions'!D21)/100)-('01_Assumptions'!D35*'01_Assumptions'!D36/100) | C19: =(('01_Assumptions'!D25/12)*12*('01_Assumptions'!D31/100))-('01_Assumptions'!D7*'01_Assumptions'!D10)-(0.5*('01_Assumptions'!E18*'01_Assumptions'!D33)/'01_Assumptions'!D23)-(0.5*('01_Assumptions'!E18*'01_Assumptions'!D33)/'01_Assumptions'!D23)-('01_Assumptions'!D19/'01_Assumptions'!D23)-((('01_Assumptions'!D25/12)*12*('01_Assumptions'!D31/100))*('01_Assumptions'!D20+'01_Assumptions'!D21)/100)-('01_Assumptions'!D35*'01_Assumptions'!D36/100) | D19: =ABS(C19-B19)
A20: A09: Compliance/legal cost | B20: =(('01_Assumptions'!D25/12)*12*('01_Assumptions'!D31/100))-('01_Assumptions'!D7*'01_Assumptions'!D10)-(0.5*('01_Assumptions'!D18*'01_Assumptions'!D33)/'01_Assumptions'!D23)-(0.5*('01_Assumptions'!D18*'01_Assumptions'!D33)/'01_Assumptions'!D23)-('01_Assumptions'!C19/'01_Assumptions'!D23)-((('01_Assumptions'!D25/12)*12*('01_Assumptions'!D31/100))*('01_Assumptions'!D20+'01_Assumptions'!D21)/100)-('01_Assumptions'!D35*'01_Assumptions'!D36/100) | C20: =(('01_Assumptions'!D25/12)*12*('01_Assumptions'!D31/100))-('01_Assumptions'!D7*'01_Assumptions'!D10)-(0.5*('01_Assumptions'!D18*'01_Assumptions'!D33)/'01_Assumptions'!D23)-(0.5*('01_Assumptions'!D18*'01_Assumptions'!D33)/'01_Assumptions'!D23)-('01_Assumptions'!E19/'01_Assumptions'!D23)-((('01_Assumptions'!D25/12)*12*('01_Assumptions'!D31/100))*('01_Assumptions'!D20+'01_Assumptions'!D21)/100)-('01_Assumptions'!D35*'01_Assumptions'!D36/100) | D20: =ABS(C20-B20)
A22: Rank by Swing (abs $) column D above to identify dominant assumptions for this combo (largest swing = most decision-relevant to validate first).

Sheet 06_Sources
A1: Sources & Provenance
A2: Every quantitative input traces to one of: (1) an external benchmark cited in research/comparable_notes.md, (2) an explicit analytic placeholder (labeled), or (3) a lead-judgment policy lever. No cell in this workbook represents confirmed Legion internal data.
A4: Assumption ID | B4: Assumption | C4: Status | D4: Source (as recorded in 01_Assumptions)
A5: A01 | B5: Traditional clinician visit cost (COGS) | C5: ceo_directional | D5: CEO-provided directional data (Phase 5, 2026-07-08, data/ceo_data_integration.md #5): ~$74 blended provider COGS per synchronous visit, ~52-53% visit gross margin on ~$153/visit revenue -- internal cross-check passes: (153-74)/153=51.6%, matches CEO's stated 52-53%. REPLACES the prior external telehealth-benchmark placeholder (was $90/150/250, Talkiatry/CareClinic/TherapyRoute anchor). Base=$74 is the CEO point estimate; low=$70/high=$85 are a modest variance band around that single blended figure (not independently sourced -- CEO gave one number, not a range).
A6: A02 | B6: AI-supported clinician visit cost (COGS) | C6: ceo_directional | D6: CEO-provided directional data (Phase 5, 2026-07-08, data/ceo_data_integration.md #6): AI-leverage assumption ~2x visits/hour -> ~$37 COGS/visit, ~76% gross margin on $153/visit revenue -- internal cross-check passes: (153-37)/153=75.8%, matches CEO's stated '75%+' target. REPLACES the prior unsourced clinician-time-compression placeholder (was $50/90/140). Base=$37 is the CEO point estimate; low=$32/high=$45 are a modest variance band around that single figure (not independently sourced).
A7: A02b | B7: Mostly-AI-driven care episode cost | C7: ceo_directional_derived | D7: DERIVED, Phase 5 (2026-07-08, data/ceo_data_integration.md #7): fully-loaded episode cost = $1 token/compute cost (CEO data point, compute only) + escalation-allocated human-review cost. Derivation shown explicitly since no Legion escalation-rate figure exists: model an escalated episode as bumping to a full AI-supported-clinician-visit-equivalent review at the A02 base rate (the '$37-leverage cost'), scaled by an illustrative escalation rate (analyst parameter, NOT CEO-sourced) -- low: ~2.7% x $37=$1.00 (+$1 token=$2.00); base: ~18.9% x $37=$7.00 (+$1=$8.00); high: ~64.9% x $37=$24.00 (+$1=$25.00). This lands inside the CEO's own framing ('even generously loaded, episode cost lands ~$2-25') and REPLACES the prior $15/35/75 external-benchmark placeholder. The $1 token input is CEO-directional; the escalation-rate parameter is analyst-derived/illustrative pending a real Legion escalation-rate figure.
A8: A03 | B8: Traditional pathway visits per patient per year | C8: ceo_directional | D8: CEO-provided directional data (Phase 5, 2026-07-08, data/ceo_data_integration.md #2/#3), REPLACES the external-benchmark placeholder (was 4/8/16). Base=5.3 = CEO's stated historical AVERAGE completed visits per patient (implies a ~5-month typical episode per CEO framing). High=13.2 = CEO's stated continuously-active/mature-cohort run-rate (1.08-1.13 completed visits/active-patient/month x 12 = ~13.0-13.6/yr; midpoint used). Low=4 is retained from the prior placeholder's low end as a labeled conservative floor (the CEO did not provide a below-average figure). TENSION, DO NOT SILENTLY BLEND (see model_readme.md v3): base (5.3) is a historical AVERAGE-patient annual rate across a full patient lifecycle; high (13.2) is the rate for a DIFFERENT population -- a patient continuously active all year (mature/retained cohort) -- not simply a more-intensive version of the same average patient. A29/A30 (mature-cohort booked/GM LTV-to-CAC) imply mature-cohort lifetime visits of ~13.2 (2,025/153), ~2.5x the 5.3 historical average; base and high are kept separate per lead direction rather than blended into one number.
A9: A03b | B9: AI-supported pathway visits per patient per year | C9: placeholder_unresolved | D9: PLACEHOLDER pending Legion data. Assumes AI-supported model enables higher-frequency, shorter touchpoints than traditional cadence; no Legion or external source specific to this pathway definition.
A10: A04 | B10: Mostly-AI-driven care episodes per patient per year | C10: placeholder_unresolved | D10: PLACEHOLDER pending Legion data. A 'care episode' here is a bundled unit of AI-driven care (e.g., an AI-led assessment/check-in cycle), analogous in scope to a clinician visit but lower-cost/lower-touch, NOT a single chat message. Range set below A03 (traditional visit cadence) per decision_framework.md's explicit qualitative ordering that the mostly-AI-driven pathway carries the LOWEST relative cost of the three pathways; no direct external benchmark exists for episode frequency specifically, so the range is an analytic placeholder anchored to that qualitative constraint.
A11: A05 | B11: Sponsor ARPU (fixed-fee sponsorship per exposed patient) | C11: estimated_external | D11: comparable_notes.md: GoodRx pharma-solutions ARPU ~$15/user/yr (derived); high case assumes multi-sponsor stacking (estimate)
A12: A06 | B12: Programmatic health eCPM (patient-vertical contextual) | C12: estimated_external | D12: comparable_notes.md: Facebook healthcare / patient-health-vertical CPM benchmarks; do NOT use physician CPMs ($70-1000+)
A13: A06b | B13: Ad sessions per patient per year (Model A exposure volume) | C13: placeholder_unresolved | D13: PLACEHOLDER. Low/base derived from A03/A03b/A04 order-of-magnitude (roughly monthly to several-times-weekly touchpoints); no Legion product-usage data exists yet. HIGH END WIDENED post strategy_red_team.md Attack 1.3 (2026-07-07 v2 revision): 150/yr was anchored to visit-based cadences and did not represent how a daily-use ambient-engagement AI companion/chat product might actually be opened; 450/yr (~1.2x/day) represents that daily-use ceiling instead. Still no Legion product-usage data exists for either end.
A14: A06c | B14: Ads served per session | C14: placeholder_external | D14: PLACEHOLDER external analogy to typical content-page ad density (display/native); not Legion-specific and no clinical-workflow ad placement has been designed or approved.
A15: A06d | B15: Ad fill rate | C15: placeholder_external | D15: PLACEHOLDER general programmatic display fill-rate norms (50-90% typical range cited across ad-tech industry sources); not health-vertical specific. Stored as 0-100 (not 0-1) for consistency with other pct01-converted assumptions (A07/A14/A19/A21/A22) in scenarios.py/sensitivity.py.
... A40: A30 | B40: Mature-cohort gross-margin LTV/CAC multiple | C40: ceo_directional | D40: CEO-provided directional data (Phase 5, 2026-07-08, data/ceo_data_integration.md #9): mature-cohort gross-margin LTV/CAC ~4.2x. Single point estimate (no range given). Implies gross-margin LTV ~= 4.2 x $250 (A28) = $1,050/patient. Context/cross-check only -- not wired into any pathway/model formula in model.py.
A42: Key External Anchors Referenced (see research/comparable_notes.md for full detail)
A43: - GoodRx pharma-manufacturer-solutions ARPU proxy: ~$15/patient/yr [DERIVED, third-party-sourced] -> A05 base.
A44: - Facebook / patient-health-vertical contextual eCPM: $20-45 [Third-party estimate] -> A06 range. Do NOT use physician CPMs ($70-1,000+, OpenEvidence/Doximity) for a patient audience.
A45: - Employer/payer PEPM benchmark: EAP $3-9 PEPM ($36-108/yr) to Lyra/Spring Health premium $120-350/mo ($1,440-4,200/yr) [Third-party estimates] -> A15 range.
A46: - Pharma agency retainer / CSO contract-size ranges ($5K/mo-$50M) -> A08, A24 order-of-magnitude anchors.
A47: - GoodRx FTC Health Breach Notification Rule enforcement (2023) and Cerebral FTC action (2024): regulatory precedent informing A09 compliance-cost high end and the trust-churn framing (A10/A11) — not used to derive a numeric trust-loss estimate (no such benchmark exists; A10/A11 remain placeholder_unresolved pending a patient concept test).
